AUTHORS
LICENSE
MANIFEST.in
README.rst
setup.py
fblib/__init__.py
fblib/core.py
fblib.egg-info/PKG-INFO
fblib.egg-info/SOURCES.txt
fblib.egg-info/dependency_links.txt
fblib.egg-info/top_level.txt
tests/tests.py