Metadata-Version: 1.1
Name: fblib
Version: 0.9.4
Summary: Alternative version of Facebook Python SDK
Home-page: https://github.com/0xKirill/fblib
Author: Kirill Karmadonov
Author-email: kirill@live.com
License: Copyright (c) 2012 Kirill Karmadonov.
